Metadata-Version: 1.0
Name: Binom-Gauss-distributions-bySawsan
Version: 1.0
Summary: Binomial and Gaussian distributions
Home-page: UNKNOWN
Author: Sawsan Omira
Author-email: sawsanemail@example.com
License: UNKNOWN
Platform: UNKNOWN
